nonlincausality/__init__.py
nonlincausality/nonlincausality.py
nonlincausality/results.py
nonlincausality/utils.py
nonlincausality-2.0.2.dist-info/LICENSE.txt
nonlincausality-2.0.2.dist-info/METADATA
nonlincausality-2.0.2.dist-info/WHEEL
nonlincausality-2.0.2.dist-info/top_level.txt
nonlincausality-2.0.2.dist-info/RECORD
