Metadata-Version: 2.1
Name: nonlincausality
Version: 2.0.2
Summary: Python package for Granger causality test with nonlinear (neural networks) forecasting methods.
Home-page: https://github.com/mrosol/Nonlincausality
Author: Maciej Rosoł
Author-email: mrosol5@gmail.com
License: MIT
Keywords: Granger causality neural networks nonlinear forecasting signals
Classifier: Development Status :: 3 - Alpha
Classifier: License :: OSI Approved :: MIT License
Classifier: Programming Language :: Python
Classifier: Programming Language :: Python :: 3.7
Classifier: Topic :: Scientific/Engineering
Classifier: Topic :: Scientific/Engineering :: Information Analysis
Classifier: Topic :: Software Development :: Libraries
Classifier: Topic :: Software Development :: Libraries :: Python Modules
Classifier: Intended Audience :: Developers
Requires-Python: >=3.6
License-File: LICENSE.txt
